simpeg_archive/DataMisfit.py
simpeg_archive/Directives.py
simpeg_archive/Fields.py
simpeg_archive/InvProblem.py
simpeg_archive/Inversion.py
simpeg_archive/Maps.py
simpeg_archive/Mesh/MeshIO.py
simpeg_archive/Models.py
simpeg_archive/ObjectiveFunction.py
simpeg_archive/Optimization.py
simpeg_archive/Problem.py
simpeg_archive/Props.py
simpeg_archive/Regularization.py
simpeg_archive/Survey.py
simpeg_archive/Tests.py
simpeg_archive/__init__.py
simpeg_archive/simpegEM1D/DigFilter.py
simpeg_archive/simpegEM1D/EM1D.py
simpeg_archive/simpegEM1D/EM1DAnalytics.py
simpeg_archive/simpegEM1D/EM1DSimulation.py
simpeg_archive/simpegEM1D/Fortran/m_rTE_Fortran.f90
simpeg_archive/simpegEM1D/GlobalEM1D.py
simpeg_archive/simpegEM1D/IO.py
simpeg_archive/simpegEM1D/Kernels.py
simpeg_archive/simpegEM1D/KnownSystems.py
simpeg_archive/simpegEM1D/RTEfun.py
simpeg_archive/simpegEM1D/RTEfun_vec.py
simpeg_archive/simpegEM1D/Regularization.py
simpeg_archive/simpegEM1D/Survey.py
simpeg_archive/simpegEM1D/Utils1D.py
simpeg_archive/simpegEM1D/Waveform.py
simpeg_archive/simpegEM1D/Waveforms.py
simpeg_archive/simpegEM1D/__init__.py
simpeg_archive/simpegEM1D/dummy.py
simpeg_archive/utils/CounterUtils.py
simpeg_archive/utils/ModelBuilder.py
simpeg_archive/utils/PlotUtils.py
simpeg_archive/utils/SolverUtils.py
simpeg_archive/utils/__init__.py
simpeg_archive/utils/codeutils.py
simpeg_archive/utils/coordutils.py
simpeg_archive/utils/curvutils.py
simpeg_archive/utils/io_utils.py
simpeg_archive/utils/matutils.py
simpeg_archive/utils/meshutils.py
simpeg_archive/utils/modelutils.py
simpeg_archive/utils/printinfo.py
simpeg_archive-0.11.0.1.dist-info/AUTHORS.rst
simpeg_archive-0.11.0.1.dist-info/LICENSE
simpeg_archive-0.11.0.1.dist-info/METADATA
simpeg_archive-0.11.0.1.dist-info/WHEEL
simpeg_archive-0.11.0.1.dist-info/RECORD
