Metadata-Version: 2.1
Name: simpeg_archive
Version: 0.11.0.1
Summary: Mira fork of SimPEG: Simulation and Parameter Estimation in Geophysics
Home-page: http://simpeg.xyz/
License: MIT
Keywords: geophysics inverse problem
Author: Rowan Cockett
Author-email: rowanc1@gmail.com
Classifier: Development Status :: 4 - Beta
Classifier: Intended Audience :: Developers
Classifier: Intended Audience :: Science/Research
Classifier: License :: OSI Approved :: MIT License
Classifier: Natural Language :: English
Classifier: Operating System :: MacOS
Classifier: Operating System :: Microsoft :: Windows
Classifier: Operating System :: POSIX
Classifier: Operating System :: Unix
Classifier: Programming Language :: Python
Classifier: Programming Language :: Python :: 2
Classifier: Programming Language :: Python :: 2.7
Classifier: Programming Language :: Python :: 3
Classifier: Programming Language :: Python :: 3.4
Classifier: Programming Language :: Python :: 3.5
Classifier: Programming Language :: Python :: 3.6
Classifier: Programming Language :: Python :: 3.7
Classifier: Programming Language :: Python :: 3.8
Classifier: Programming Language :: Python :: 3.9
Classifier: Programming Language :: Python :: 3.10
Classifier: Programming Language :: Python :: 3.11
Classifier: Programming Language :: Python :: 3.12
Classifier: Programming Language :: Python :: 3.13
Classifier: Topic :: Scientific/Engineering
Classifier: Topic :: Scientific/Engineering :: Mathematics
Classifier: Topic :: Scientific/Engineering :: Physics
Provides-Extra: regular
Requires-Dist: discretize
Requires-Dist: matplotlib ; extra == "regular"
Requires-Dist: numpy (>=1.7)
Requires-Dist: properties[math] (>=0.3.1b2)
Requires-Dist: pymatsolver (>=0.1.1)
Requires-Dist: scipy (>=0.13)
Project-URL: Documentation, https://docs.simpeg.xyz/
Project-URL: Repository, http://github.com/simpeg/simpeg
